README.rst
mmv.c
pmapi.c
pmda.c
pmgui.c
pmi.c
setup.py
pcp/__init__.py
pcp/mmv.py
pcp/pmapi.py
pcp/pmcc.py
pcp/pmconfig.py
pcp/pmda.py
pcp/pmgui.py
pcp/pmi.py
pcp.egg-info/PKG-INFO
pcp.egg-info/SOURCES.txt
pcp.egg-info/dependency_links.txt
pcp.egg-info/top_level.txt